LICENSE
poetryx/__init__.py
poetryx/cli/__init__.py
poetryx/cli/commands.py
poetryx/cli/typer_cli.py
poetryx/file/__init__.py
poetryx/file/config.toml
poetryx/file/file_config.py
poetryx/file/file_manager.py
poetryx-0.1.0.dist-info/LICENSE
poetryx-0.1.0.dist-info/METADATA
poetryx-0.1.0.dist-info/WHEEL
poetryx-0.1.0.dist-info/entry_points.txt
poetryx-0.1.0.dist-info/RECORD
