Metadata-Version: 2.1
Name: poetryx
Version: 0.1.0
Summary: CLI wrapper built on-top of Poetry enabling common utilities and application scaffolding for enhanced productivity.
Home-page: https://github.com/nachatz/poetryx
License: Apache-2.0
Author: Nikolas Achatz
Requires-Python: >=3.10,<4.0
Classifier: License :: OSI Approved :: Apache Software License
Classifier: Programming Language :: Python :: 3
Classifier: Programming Language :: Python :: 3.10
Classifier: Programming Language :: Python :: 3.11
Classifier: Programming Language :: Python :: 3.12
Requires-Dist: pydantic (>=2.3,<3.0)
Requires-Dist: toml (>=0.10.2,<0.11.0)
Requires-Dist: typer (>=0.12.3,<0.13.0)
Project-URL: Repository, https://github.com/nachatz/poetryx
